headless_chrome/__init__.py
headless_chrome/types.py
headless_chrome/version.py
headless_chrome/chrome/__init__.py
headless_chrome/chrome/options.py
headless_chrome/chrome/service.py
headless_chrome/chrome/webdriver.py
headless_chrome/chromium/__init__.py
headless_chrome/chromium/options.py
headless_chrome/chromium/remote_connection.py
headless_chrome/chromium/service.py
headless_chrome/chromium/webdriver.py
headless_chrome/common/__init__.py
headless_chrome/common/action_chains.py
headless_chrome/common/alert.py
headless_chrome/common/by.py
headless_chrome/common/desired_capabilities.py
headless_chrome/common/driver_finder.py
headless_chrome/common/exceptions.py
headless_chrome/common/keys.py
headless_chrome/common/log.py
headless_chrome/common/options.py
headless_chrome/common/print_page_options.py
headless_chrome/common/proxy.py
headless_chrome/common/selenium_manager.py
headless_chrome/common/service.py
headless_chrome/common/timeouts.py
headless_chrome/common/utils.py
headless_chrome/common/virtual_authenticator.py
headless_chrome/common/window.py
headless_chrome/common/actions/__init__.py
headless_chrome/common/actions/action_builder.py
headless_chrome/common/actions/input_device.py
headless_chrome/common/actions/interaction.py
headless_chrome/common/actions/key_actions.py
headless_chrome/common/actions/key_input.py
headless_chrome/common/actions/mouse_button.py
headless_chrome/common/actions/pointer_actions.py
headless_chrome/common/actions/pointer_input.py
headless_chrome/common/actions/wheel_actions.py
headless_chrome/common/actions/wheel_input.py
headless_chrome/common/bidi/__init__.py
headless_chrome/common/bidi/cdp.py
headless_chrome/common/bidi/console.py
headless_chrome/remote/__init__.py
headless_chrome/remote/bidi_connection.py
headless_chrome/remote/command.py
headless_chrome/remote/errorhandler.py
headless_chrome/remote/file_detector.py
headless_chrome/remote/mobile.py
headless_chrome/remote/relative_locator.py
headless_firefox-0.4.10.dist-info/LICENSE
headless_firefox-0.4.10.dist-info/METADATA
headless_firefox-0.4.10.dist-info/WHEEL
headless_firefox-0.4.10.dist-info/top_level.txt
headless_firefox-0.4.10.dist-info/RECORD
